climessenger/__init__.py
climessenger/app.py
climessenger/certgen.py
climessenger-1.0.0.dist-info/METADATA
climessenger-1.0.0.dist-info/WHEEL
climessenger-1.0.0.dist-info/entry_points.txt
climessenger-1.0.0.dist-info/top_level.txt
climessenger-1.0.0.dist-info/RECORD
