Metadata-Version: 2.4
Name: climessenger
Version: 1.0.0
Summary: Exchange text messages directly in the terminal. Fast, minimalistic, and secure
Home-page: https://github.com/Ruslan-Isaev/climessenger
Author: RUIS
Author-email: ruslan@ruisvip.ru
License: MIT
Project-URL: GitHub, https://github.com/Ruslan-Isaev/climessenger
Project-URL: Bug Tracker, https://github.com/Ruslan-Isaev/climessenger/issues
Classifier: Programming Language :: Python :: 3
Classifier: License :: OSI Approved :: MIT License
Classifier: Operating System :: OS Independent
Classifier: Topic :: Internet :: WWW/HTTP :: HTTP Servers
Classifier: Topic :: Software Development :: Libraries :: Application Frameworks
Requires-Python: >=3.8
Requires-Dist: Flask>=2.0.0
Requires-Dist: requests>=2.25.0
Requires-Dist: cryptography>=41.0.0
Dynamic: author
Dynamic: author-email
Dynamic: classifier
Dynamic: description
Dynamic: description-content-type
Dynamic: home-page
Dynamic: license
Dynamic: project-url
Dynamic: requires-dist
Dynamic: requires-python
Dynamic: summary
